[
  {
    "pwo_number": "Demand Number: 10000",
    "platform_technology": "Workday",
    "high_level_scope": "Support services for workday",
    "contract_name": "Managed Services for Workday and other HR applications",
    "contract_type": "SOW",
    "contract_start_date": "2023-11-01 00:00:00",
    "contract_end_date": "2026-12-31 00:00:00",
    "managed_by": "SL",
    "sow_value_eur": "3960775.720390051",
    "sow_currency": "INR",
    "sow_value_lc": "361500000.0",
    "fx": "91.27",
    "type_of_contract_l1": "IT Services",
    "type_of_contract_l2": "AM services",
    "user_based_license": "No",
    "contractual_commercial_model": "Fixed"
  },
  {
    "pwo_number": "10122011JF01",
    "contract_name": "Software License Review",
    "contract_type": "SOW",
    "contract_start_date": "2023-12-31 00:00:00",
    "contract_end_date": "2026-12-31 00:00:00",
    "managed_by": "SL",
    "sow_value_eur": "21505101.215733018",
    "sow_currency": "GBP",
    "sow_value_lc": "18042779.92",
    "fx": "0.839",
    "type_of_contract_l1": "IT Software",
    "type_of_contract_l2": "Licenses",
    "user_based_license": "Yes",
    "contractual_commercial_model": "Fixed"
  },
  {
    "pwo_number": "4948686",
    "contract_name": "Software License",
    "contract_type": "Quote",
    "contract_start_date": "2025-01-07 00:00:00",
    "contract_end_date": "2025-12-31 00:00:00",
    "managed_by": "SL",
    "sow_value_eur": "3532282.669845054",
    "sow_currency": "GBP",
    "sow_value_lc": "2963585.16",
    "fx": "0.839",
    "type_of_contract_l1": "IT Software",
    "type_of_contract_l2": "Licenses",
    "contractual_commercial_model": "Fixed"
  },
  {
    "pwo_number": "QUO-002307",
    "platform_technology": "Quality One ELA",
    "high_level_scope": "Renewal of Veeva Quality",
    "contract_name": "Vault QualityOne ELA",
    "contract_type": "Order Form",
    "contract_start_date": "2025-03-01 00:00:00",
    "contract_end_date": "2026-02-28 00:00:00",
    "managed_by": "SL",
    "sow_value_eur": "1464736.4999999998",
    "sow_currency": "USD",
    "sow_value_lc": "1350000.0",
    "fx": "1.086",
    "type_of_contract_l1": "IT Software",
    "type_of_contract_l2": "Licenses",
    "user_based_license": "Yes",
    "contractual_commercial_model": "Others"
  },
  {
    "pwo_number": "16171",
    "platform_technology": " PEGA application",
    "high_level_scope": "Pega License for 2025",
    "contract_name": "Pega License for 2025",
    "contract_type": "Demand Detail",
    "managed_by": "SL",
    "sow_value_eur": "3048316.0",
    "sow_currency": "EUR",
    "sow_value_lc": "3048316.0",
    "fx": "1.0",
    "type_of_contract_l1": "IT Software",
    "type_of_contract_l2": "Licenses",
    "contractual_commercial_model": "Fixed"
  },
  {
    "pwo_number": "Schedule #01 - CLS AI+SIT ",
    "platform_technology": "Cloud Services",
    "high_level_scope": "Subscription for Collections Cloud \u2013 Demand No. 398",
    "contract_name": "Subscription for Collections Cloud \u2013 Demand No. 398",
    "contract_type": "Order Form",
    "contract_start_date": "2025-01-01 00:00:00",
    "contract_end_date": "2025-12-31 00:00:00",
    "managed_by": "SL",
    "sow_value_eur": "2204117.486187845",
    "sow_currency": "USD",
    "sow_value_lc": "2393671.59",
    "fx": "1.086",
    "type_of_contract_l1": "IT Services",
    "type_of_contract_l2": "Cloud Hosting services",
    "contractual_commercial_model": "Fixed"
  },
  {
    "pwo_number": "2024-12-01 00:00:00",
    "platform_technology": "Blackline",
    "high_level_scope": "Blackine Saas Subscription Fees",
    "contract_name": "Solution and Enterprise pack",
    "contract_type": "Quote",
    "contract_start_date": "2024-12-31 00:00:00",
    "contract_end_date": "2025-12-31 00:00:00",
    "managed_by": "SL",
    "sow_value_eur": "3497700.0",
    "sow_currency": "EUR",
    "sow_value_lc": "3497700.0",
    "fx": "1.0",
    "type_of_contract_l1": "IT Software",
    "type_of_contract_l2": "SaaS/Subscription",
    "user_based_license": "Yes",
    "contractual_commercial_model": "Others",
    "remarks": "Ishan to review and make changes "
  },
  {
    "pwo_number": "ID0039692",
    "platform_technology": "Google workspace",
    "contract_name": "Google workspace Oct'2022 to Oct'2026",
    "contract_type": "Quote",
    "contract_start_date": "2022-10-01 00:00:00",
    "contract_end_date": "2026-10-01 00:00:00",
    "managed_by": "SL",
    "sow_value_eur": "7834642.908224077",
    "sow_currency": "GBP",
    "sow_value_lc": "6573265.4",
    "fx": "0.839",
    "type_of_contract_l1": "IT Services",
    "type_of_contract_l2": "Cloud Hosting services"
  },
  {
    "pwo_number": "Uni-SOW-1",
    "platform_technology": "Jira",
    "contract_name": "Jira License Mar 25 - Mar 26",
    "contract_type": "SOW",
    "contract_start_date": "2025-03-01 00:00:00",
    "contract_end_date": "2026-03-01 00:00:00",
    "managed_by": "SL",
    "sow_value_eur": "2938904.23572744",
    "sow_currency": "USD",
    "sow_value_lc": "3191650.0",
    "fx": "1.086",
    "type_of_contract_l1": "IT Services",
    "type_of_contract_l2": "SaaS/Subscription"
  },
  {
    "pwo_number": "DR3345713",
    "platform_technology": "Adobe",
    "high_level_scope": " ADOBE COMMERCE: CLOUD BUNDLE",
    "contract_name": " ADOBE COMMERCE: CLOUD BUNDLE",
    "contract_type": "Quote",
    "contract_start_date": "2024-03-01 00:00:00",
    "contract_end_date": "2027-02-28 00:00:00",
    "managed_by": "SL",
    "sow_value_eur": "6379404.788213627",
    "sow_currency": "USD",
    "sow_value_lc": "6928033.6",
    "fx": "1.086",
    "type_of_contract_l1": "IT Software",
    "type_of_contract_l2": "SaaS/Subscription",
    "user_based_license": "Yes",
    "contractual_commercial_model": "Fixed"
  }
]